prometeo/__init__.py
prometeo/base_client.py
prometeo/base_session.py
prometeo/client.py
prometeo/exceptions.py
prometeo/utils.py
prometeo/account_validation/__init__.py
prometeo/account_validation/client.py
prometeo/account_validation/exceptions.py
prometeo/account_validation/models.py
prometeo/account_validation/codes/__init__.py
prometeo/account_validation/codes/account_type.py
prometeo/account_validation/codes/bank.py
prometeo/account_validation/codes/country.py
prometeo/account_validation/codes/document_type.py
prometeo/banking/__init__.py
prometeo/banking/client.py
prometeo/banking/exceptions.py
prometeo/banking/models.py
prometeo/crossborder/__init__.py
prometeo/crossborder/client.py
prometeo/crossborder/exceptions.py
prometeo/crossborder/models.py
prometeo/curp/__init__.py
prometeo/curp/client.py
prometeo/curp/exceptions.py
prometeo/curp/models.py
prometeo/dian/__init__.py
prometeo/dian/client.py
prometeo/dian/models.py
prometeo/payment/__init__.py
prometeo/payment/client.py
prometeo/payment/exceptions.py
prometeo/payment/models.py
prometeo/sat/__init__.py
prometeo/sat/client.py
prometeo/sat/models.py
tests/__init__.py
tests/base_test_case.py
tests/test_base_client.py
tests/account_validation/__init__.py
tests/account_validation/test_client.py
tests/banking/__init__.py
tests/banking/test_account.py
tests/banking/test_client.py
tests/banking/test_credit_card.py
tests/banking/test_session.py
tests/crossborder/__init__.py
tests/crossborder/test_client.py
tests/curp/__init__.py
tests/curp/test_client.py
tests/dian/__init__.py
tests/dian/test_client.py
tests/dian/test_session.py
tests/payment/__init__.py
tests/payment/test_client.py
tests/sat/__init__.py
tests/sat/test_client.py
tests/sat/test_download.py
tests/sat/test_session.py
prometeo-2.0.10.dist-info/LICENSE
prometeo-2.0.10.dist-info/METADATA
prometeo-2.0.10.dist-info/WHEEL
prometeo-2.0.10.dist-info/top_level.txt
prometeo-2.0.10.dist-info/RECORD
