Metadata-Version: 2.1
Name: prometeo
Version: 2.0.10
Summary: Python client library for Prometeo
Home-page: https://github.com/prometeoapi/prometeo-python
Author: Prometeo
Author-email: dev@prometeoapi.com
Classifier: Programming Language :: Python :: 3
Classifier: Programming Language :: Python :: 2.7
Classifier: License :: OSI Approved :: MIT License
Classifier: Operating System :: OS Independent
Requires-Python: >=3.8
License-File: LICENSE
Requires-Dist: httpx <0.28.0,>=0.27.0
Requires-Dist: pydantic <3.0.0,>=2.7.2
Requires-Dist: six >=1.16.0
